whitecapella_lotto/__init__.py
whitecapella_lotto/lotto.py
whitecapella_lotto-0.2.0.dist-info/METADATA
whitecapella_lotto-0.2.0.dist-info/WHEEL
whitecapella_lotto-0.2.0.dist-info/top_level.txt
whitecapella_lotto-0.2.0.dist-info/RECORD
