Metadata-Version: 2.1
Name: whitecapella_lotto
Version: 0.2.0
Summary: Default template for PDM package
Author-email: whitecapella1 <whitecapella@naver.com>
License: MIT
Requires-Python: >=3.9
